odoo/addons/hr_course_survey/README.rst
odoo/addons/hr_course_survey/__init__.py
odoo/addons/hr_course_survey/__manifest__.py
odoo/addons/hr_course_survey/data/mail.xml
odoo/addons/hr_course_survey/i18n/ca_ES.po
odoo/addons/hr_course_survey/i18n/es.po
odoo/addons/hr_course_survey/i18n/es_PA.po
odoo/addons/hr_course_survey/i18n/hr_course_survey.pot
odoo/addons/hr_course_survey/models/__init__.py
odoo/addons/hr_course_survey/models/hr_course.py
odoo/addons/hr_course_survey/models/hr_course_attendee.py
odoo/addons/hr_course_survey/models/hr_course_schedule.py
odoo/addons/hr_course_survey/models/survey_user_input.py
odoo/addons/hr_course_survey/readme/CONTRIBUTORS.rst
odoo/addons/hr_course_survey/readme/DESCRIPTION.rst
odoo/addons/hr_course_survey/readme/USAGE.rst
odoo/addons/hr_course_survey/static/description/icon.png
odoo/addons/hr_course_survey/static/description/index.html
odoo/addons/hr_course_survey/tests/__init__.py
odoo/addons/hr_course_survey/tests/test_hr_course.py
odoo/addons/hr_course_survey/views/hr_course.xml
odoo/addons/hr_course_survey/views/hr_course_attendee.xml
odoo/addons/hr_course_survey/views/hr_course_schedule.xml
odoo14_addon_hr_course_survey-14.0.1.0.2.dist-info/METADATA
odoo14_addon_hr_course_survey-14.0.1.0.2.dist-info/WHEEL
odoo14_addon_hr_course_survey-14.0.1.0.2.dist-info/top_level.txt
odoo14_addon_hr_course_survey-14.0.1.0.2.dist-info/RECORD
